mipt2024f_4_barrect/__init__.py
mipt2024f_4_barrect/quality.py
mipt2024f_4_barrect/rectify.py
mipt2024f_4_barrect/internal/__init__.py
mipt2024f_4_barrect/internal/elliptic.py
mipt2024f_4_barrect/internal/gridgen.py
mipt2024f_4_barrect/internal/gridmap.py
mipt2024f_4_barrect/internal/warp.py
mipt2024f_4_barrect-0.1.0.dist-info/LICENSE
mipt2024f_4_barrect-0.1.0.dist-info/METADATA
mipt2024f_4_barrect-0.1.0.dist-info/WHEEL
mipt2024f_4_barrect-0.1.0.dist-info/top_level.txt
mipt2024f_4_barrect-0.1.0.dist-info/RECORD
